{"info":{"file":"app/scripts/controllers/profile.js","fileShort":"app/scripts/controllers/profile.js","fileSafe":"app_scripts_controllers_profile_js","link":"files/app_scripts_controllers_profile_js/index.html"},"complexity":{"aggregate":{"sloc":{"logical":122,"physical":197},"cyclomatic":6,"halstead":{"operators":{"distinct":16,"total":274,"identifiers":["__stripped__"]},"operands":{"distinct":142,"total":387,"identifiers":["__stripped__"]},"length":661,"vocabulary":158,"difficulty":21.802816901408452,"volume":4827.799074545065,"effort":105259.61925909523,"bugs":1.6092663581816884,"time":5847.756625505291},"params":24,"line":1,"cyclomaticDensity":4.918032786885246,"complexity":{"cyclomatic":6,"sloc":{"logical":122,"physical":197},"halstead":{"operators":{"distinct":16,"total":274,"identifiers":["__stripped__"]},"operands":{"distinct":142,"total":387,"identifiers":["__stripped__"]},"length":661,"vocabulary":158,"difficulty":21.802816901408452,"volume":4827.799074545065,"effort":105259.61925909523,"bugs":1.6092663581816884,"time":5847.756625505291}}},"functions":[{"name":"<anonymous>","sloc":{"logical":28,"physical":186},"cyclomatic":1,"halstead":{"operators":{"distinct":8,"total":45,"identifiers":["__stripped__"]},"operands":{"distinct":40,"total":55,"identifiers":["__stripped__"]},"length":100,"vocabulary":48,"difficulty":5.5,"volume":558.4962500721157,"effort":3071.7293753966364,"bugs":0.18616541669070522,"time":170.6516319664798},"params":8,"line":12,"cyclomaticDensity":3.571428571428571,"complexity":{"cyclomatic":1,"sloc":{"logical":28,"physical":186},"halstead":{"operators":{"distinct":8,"total":45,"identifiers":["__stripped__"]},"operands":{"distinct":40,"total":55,"identifiers":["__stripped__"]},"length":100,"vocabulary":48,"difficulty":5.5,"volume":558.4962500721157,"effort":3071.7293753966364,"bugs":0.18616541669070522,"time":170.6516319664798}}},{"name":"ProfileController","sloc":{"logical":18,"physical":33},"cyclomatic":1,"halstead":{"operators":{"distinct":7,"total":38,"identifiers":["__stripped__"]},"operands":{"distinct":34,"total":56,"identifiers":["__stripped__"]},"length":94,"vocabulary":41,"difficulty":5.764705882352941,"volume":503.6098884340999,"effort":2903.162886267164,"bugs":0.16786996281136662,"time":161.28682701484246},"params":4,"line":30,"cyclomaticDensity":5.555555555555555,"complexity":{"cyclomatic":1,"sloc":{"logical":18,"physical":33},"halstead":{"operators":{"distinct":7,"total":38,"identifiers":["__stripped__"]},"operands":{"distinct":34,"total":56,"identifiers":["__stripped__"]},"length":94,"vocabulary":41,"difficulty":5.764705882352941,"volume":503.6098884340999,"effort":2903.162886267164,"bugs":0.16786996281136662,"time":161.28682701484246}}},{"name":"<anonymous>","sloc":{"logical":3,"physical":5},"cyclomatic":1,"halstead":{"operators":{"distinct":4,"total":6,"identifiers":["__stripped__"]},"operands":{"distinct":8,"total":11,"identifiers":["__stripped__"]},"length":17,"vocabulary":12,"difficulty":2.75,"volume":60.94436251225966,"effort":167.59699690871406,"bugs":0.020314787504086555,"time":9.310944272706337},"params":3,"line":42,"cyclomaticDensity":33.33333333333333,"complexity":{"cyclomatic":1,"sloc":{"logical":3,"physical":5},"halstead":{"operators":{"distinct":4,"total":6,"identifiers":["__stripped__"]},"operands":{"distinct":8,"total":11,"identifiers":["__stripped__"]},"length":17,"vocabulary":12,"difficulty":2.75,"volume":60.94436251225966,"effort":167.59699690871406,"bugs":0.020314787504086555,"time":9.310944272706337}}},{"name":"<anonymous>","sloc":{"logical":1,"physical":3},"cyclomatic":1,"halstead":{"operators":{"distinct":1,"total":1,"identifiers":["__stripped__"]},"operands":{"distinct":3,"total":4,"identifiers":["__stripped__"]},"length":5,"vocabulary":4,"difficulty":0.6666666666666666,"volume":10,"effort":6.666666666666666,"bugs":0.0033333333333333335,"time":0.37037037037037035},"params":2,"line":47,"cyclomaticDensity":100,"complexity":{"cyclomatic":1,"sloc":{"logical":1,"physical":3},"halstead":{"operators":{"distinct":1,"total":1,"identifiers":["__stripped__"]},"operands":{"distinct":3,"total":4,"identifiers":["__stripped__"]},"length":5,"vocabulary":4,"difficulty":0.6666666666666666,"volume":10,"effort":6.666666666666666,"bugs":0.0033333333333333335,"time":0.37037037037037035}}},{"name":"<anonymous>","sloc":{"logical":1,"physical":3},"cyclomatic":1,"halstead":{"operators":{"distinct":2,"total":2,"identifiers":["__stripped__"]},"operands":{"distinct":3,"total":3,"identifiers":["__stripped__"]},"length":5,"vocabulary":5,"difficulty":1,"volume":11.60964047443681,"effort":11.60964047443681,"bugs":0.0038698801581456034,"time":0.6449800263576005},"params":0,"line":50,"cyclomaticDensity":100,"complexity":{"cyclomatic":1,"sloc":{"logical":1,"physical":3},"halstead":{"operators":{"distinct":2,"total":2,"identifiers":["__stripped__"]},"operands":{"distinct":3,"total":3,"identifiers":["__stripped__"]},"length":5,"vocabulary":5,"difficulty":1,"volume":11.60964047443681,"effort":11.60964047443681,"bugs":0.0038698801581456034,"time":0.6449800263576005}}},{"name":"<anonymous>","sloc":{"logical":1,"physical":3},"cyclomatic":1,"halstead":{"operators":{"distinct":1,"total":1,"identifiers":["__stripped__"]},"operands":{"distinct":3,"total":4,"identifiers":["__stripped__"]},"length":5,"vocabulary":4,"difficulty":0.6666666666666666,"volume":10,"effort":6.666666666666666,"bugs":0.0033333333333333335,"time":0.37037037037037035},"params":2,"line":59,"cyclomaticDensity":100,"complexity":{"cyclomatic":1,"sloc":{"logical":1,"physical":3},"halstead":{"operators":{"distinct":1,"total":1,"identifiers":["__stripped__"]},"operands":{"distinct":3,"total":4,"identifiers":["__stripped__"]},"length":5,"vocabulary":4,"difficulty":0.6666666666666666,"volume":10,"effort":6.666666666666666,"bugs":0.0033333333333333335,"time":0.37037037037037035}}},{"name":"toggleInvert","sloc":{"logical":8,"physical":13},"cyclomatic":4,"halstead":{"operators":{"distinct":8,"total":18,"identifiers":["__stripped__"]},"operands":{"distinct":7,"total":17,"identifiers":["__stripped__"]},"length":35,"vocabulary":15,"difficulty":9.714285714285714,"volume":136.74117084629816,"effort":1328.3428025068963,"bugs":0.045580390282099384,"time":73.79682236149424},"params":0,"line":69,"cyclomaticDensity":50,"complexity":{"cyclomatic":4,"sloc":{"logical":8,"physical":13},"halstead":{"operators":{"distinct":8,"total":18,"identifiers":["__stripped__"]},"operands":{"distinct":7,"total":17,"identifiers":["__stripped__"]},"length":35,"vocabulary":15,"difficulty":9.714285714285714,"volume":136.74117084629816,"effort":1328.3428025068963,"bugs":0.045580390282099384,"time":73.79682236149424}}},{"name":"render","sloc":{"logical":2,"physical":15},"cyclomatic":1,"halstead":{"operators":{"distinct":4,"total":4,"identifiers":["__stripped__"]},"operands":{"distinct":2,"total":3,"identifiers":["__stripped__"]},"length":7,"vocabulary":6,"difficulty":3,"volume":18.094737505048094,"effort":54.28421251514428,"bugs":0.006031579168349364,"time":3.0157895841746822},"params":0,"line":87,"cyclomaticDensity":50,"complexity":{"cyclomatic":1,"sloc":{"logical":2,"physical":15},"halstead":{"operators":{"distinct":4,"total":4,"identifiers":["__stripped__"]},"operands":{"distinct":2,"total":3,"identifiers":["__stripped__"]},"length":7,"vocabulary":6,"difficulty":3,"volume":18.094737505048094,"effort":54.28421251514428,"bugs":0.006031579168349364,"time":3.0157895841746822}}},{"name":"animate","sloc":{"logical":4,"physical":12},"cyclomatic":1,"halstead":{"operators":{"distinct":3,"total":8,"identifiers":["__stripped__"]},"operands":{"distinct":12,"total":12,"identifiers":["__stripped__"]},"length":20,"vocabulary":15,"difficulty":1.5,"volume":78.13781191217038,"effort":117.20671786825557,"bugs":0.026045937304056792,"time":6.511484326014198},"params":0,"line":88,"cyclomaticDensity":25,"complexity":{"cyclomatic":1,"sloc":{"logical":4,"physical":12},"halstead":{"operators":{"distinct":3,"total":8,"identifiers":["__stripped__"]},"operands":{"distinct":12,"total":12,"identifiers":["__stripped__"]},"length":20,"vocabulary":15,"difficulty":1.5,"volume":78.13781191217038,"effort":117.20671786825557,"bugs":0.026045937304056792,"time":6.511484326014198}}},{"name":"<anonymous>","sloc":{"logical":1,"physical":7},"cyclomatic":1,"halstead":{"operators":{"distinct":2,"total":3,"identifiers":["__stripped__"]},"operands":{"distinct":5,"total":6,"identifiers":["__stripped__"]},"length":9,"vocabulary":7,"difficulty":1.2,"volume":25.26619429851844,"effort":30.319433158222125,"bugs":0.008422064766172813,"time":1.6844129532345624},"params":1,"line":91,"cyclomaticDensity":100,"complexity":{"cyclomatic":1,"sloc":{"logical":1,"physical":7},"halstead":{"operators":{"distinct":2,"total":3,"identifiers":["__stripped__"]},"operands":{"distinct":5,"total":6,"identifiers":["__stripped__"]},"length":9,"vocabulary":7,"difficulty":1.2,"volume":25.26619429851844,"effort":30.319433158222125,"bugs":0.008422064766172813,"time":1.6844129532345624}}},{"name":"clearScene","sloc":{"logical":1,"physical":5},"cyclomatic":1,"halstead":{"operators":{"distinct":3,"total":3,"identifiers":["__stripped__"]},"operands":{"distinct":4,"total":4,"identifiers":["__stripped__"]},"length":7,"vocabulary":7,"difficulty":1.5,"volume":19.651484454403228,"effort":29.47722668160484,"bugs":0.00655049481813441,"time":1.6376237045336022},"params":0,"line":107,"cyclomaticDensity":100,"complexity":{"cyclomatic":1,"sloc":{"logical":1,"physical":5},"halstead":{"operators":{"distinct":3,"total":3,"identifiers":["__stripped__"]},"operands":{"distinct":4,"total":4,"identifiers":["__stripped__"]},"length":7,"vocabulary":7,"difficulty":1.5,"volume":19.651484454403228,"effort":29.47722668160484,"bugs":0.00655049481813441,"time":1.6376237045336022}}},{"name":"<anonymous>","sloc":{"logical":1,"physical":3},"cyclomatic":1,"halstead":{"operators":{"distinct":1,"total":1,"identifiers":["__stripped__"]},"operands":{"distinct":2,"total":3,"identifiers":["__stripped__"]},"length":4,"vocabulary":3,"difficulty":0.75,"volume":6.339850002884625,"effort":4.754887502163469,"bugs":0.002113283334294875,"time":0.2641604167868594},"params":1,"line":108,"cyclomaticDensity":100,"complexity":{"cyclomatic":1,"sloc":{"logical":1,"physical":3},"halstead":{"operators":{"distinct":1,"total":1,"identifiers":["__stripped__"]},"operands":{"distinct":2,"total":3,"identifiers":["__stripped__"]},"length":4,"vocabulary":3,"difficulty":0.75,"volume":6.339850002884625,"effort":4.754887502163469,"bugs":0.002113283334294875,"time":0.2641604167868594}}},{"name":"drawProfile","sloc":{"logical":3,"physical":5},"cyclomatic":1,"halstead":{"operators":{"distinct":3,"total":6,"identifiers":["__stripped__"]},"operands":{"distinct":6,"total":10,"identifiers":["__stripped__"]},"length":16,"vocabulary":9,"difficulty":2.5,"volume":50.718800023077,"effort":126.7970000576925,"bugs":0.016906266674359,"time":7.044277780982917},"params":1,"line":113,"cyclomaticDensity":33.33333333333333,"complexity":{"cyclomatic":1,"sloc":{"logical":3,"physical":5},"halstead":{"operators":{"distinct":3,"total":6,"identifiers":["__stripped__"]},"operands":{"distinct":6,"total":10,"identifiers":["__stripped__"]},"length":16,"vocabulary":9,"difficulty":2.5,"volume":50.718800023077,"effort":126.7970000576925,"bugs":0.016906266674359,"time":7.044277780982917}}},{"name":"draw","sloc":{"logical":3,"physical":5},"cyclomatic":1,"halstead":{"operators":{"distinct":3,"total":4,"identifiers":["__stripped__"]},"operands":{"distinct":5,"total":7,"identifiers":["__stripped__"]},"length":11,"vocabulary":8,"difficulty":2.0999999999999996,"volume":33,"effort":69.29999999999998,"bugs":0.011,"time":3.849999999999999},"params":1,"line":119,"cyclomaticDensity":33.33333333333333,"complexity":{"cyclomatic":1,"sloc":{"logical":3,"physical":5},"halstead":{"operators":{"distinct":3,"total":4,"identifiers":["__stripped__"]},"operands":{"distinct":5,"total":7,"identifiers":["__stripped__"]},"length":11,"vocabulary":8,"difficulty":2.0999999999999996,"volume":33,"effort":69.29999999999998,"bugs":0.011,"time":3.849999999999999}}},{"name":"remove","sloc":{"logical":7,"physical":9},"cyclomatic":3,"halstead":{"operators":{"distinct":7,"total":19,"identifiers":["__stripped__"]},"operands":{"distinct":7,"total":20,"identifiers":["__stripped__"]},"length":39,"vocabulary":14,"difficulty":10,"volume":148.48684196024655,"effort":1484.8684196024656,"bugs":0.04949561398674885,"time":82.49268997791475},"params":1,"line":125,"cyclomaticDensity":42.857142857142854,"complexity":{"cyclomatic":3,"sloc":{"logical":7,"physical":9},"halstead":{"operators":{"distinct":7,"total":19,"identifiers":["__stripped__"]},"operands":{"distinct":7,"total":20,"identifiers":["__stripped__"]},"length":39,"vocabulary":14,"difficulty":10,"volume":148.48684196024655,"effort":1484.8684196024656,"bugs":0.04949561398674885,"time":82.49268997791475}}},{"name":"initScene","sloc":{"logical":19,"physical":29},"cyclomatic":1,"halstead":{"operators":{"distinct":6,"total":54,"identifiers":["__stripped__"]},"operands":{"distinct":37,"total":79,"identifiers":["__stripped__"]},"length":133,"vocabulary":43,"difficulty":6.405405405405405,"volume":721.6932123753791,"effort":4622.737603593644,"bugs":0.24056440412512636,"time":256.81875575520246},"params":0,"line":136,"cyclomaticDensity":5.263157894736842,"complexity":{"cyclomatic":1,"sloc":{"logical":19,"physical":29},"halstead":{"operators":{"distinct":6,"total":54,"identifiers":["__stripped__"]},"operands":{"distinct":37,"total":79,"identifiers":["__stripped__"]},"length":133,"vocabulary":43,"difficulty":6.405405405405405,"volume":721.6932123753791,"effort":4622.737603593644,"bugs":0.24056440412512636,"time":256.81875575520246}}},{"name":"initCamera","sloc":{"logical":6,"physical":8},"cyclomatic":1,"halstead":{"operators":{"distinct":6,"total":20,"identifiers":["__stripped__"]},"operands":{"distinct":15,"total":27,"identifiers":["__stripped__"]},"length":47,"vocabulary":21,"difficulty":5.4,"volume":206.43891887060175,"effort":1114.7701619012496,"bugs":0.06881297295686725,"time":61.931675661180535},"params":0,"line":166,"cyclomaticDensity":16.666666666666664,"complexity":{"cyclomatic":1,"sloc":{"logical":6,"physical":8},"halstead":{"operators":{"distinct":6,"total":20,"identifiers":["__stripped__"]},"operands":{"distinct":15,"total":27,"identifiers":["__stripped__"]},"length":47,"vocabulary":21,"difficulty":5.4,"volume":206.43891887060175,"effort":1114.7701619012496,"bugs":0.06881297295686725,"time":61.931675661180535}}},{"name":"initRenderer","sloc":{"logical":9,"physical":12},"cyclomatic":1,"halstead":{"operators":{"distinct":5,"total":24,"identifiers":["__stripped__"]},"operands":{"distinct":18,"total":32,"identifiers":["__stripped__"]},"length":56,"vocabulary":23,"difficulty":4.444444444444445,"volume":253.31946953919274,"effort":1125.864309063079,"bugs":0.08443982317973091,"time":62.54801717017105},"params":0,"line":175,"cyclomaticDensity":11.11111111111111,"complexity":{"cyclomatic":1,"sloc":{"logical":9,"physical":12},"halstead":{"operators":{"distinct":5,"total":24,"identifiers":["__stripped__"]},"operands":{"distinct":18,"total":32,"identifiers":["__stripped__"]},"length":56,"vocabulary":23,"difficulty":4.444444444444445,"volume":253.31946953919274,"effort":1125.864309063079,"bugs":0.08443982317973091,"time":62.54801717017105}}},{"name":"initControls","sloc":{"logical":5,"physical":7},"cyclomatic":1,"halstead":{"operators":{"distinct":3,"total":14,"identifiers":["__stripped__"]},"operands":{"distinct":13,"total":22,"identifiers":["__stripped__"]},"length":36,"vocabulary":16,"difficulty":2.5384615384615383,"volume":144,"effort":365.53846153846155,"bugs":0.048,"time":20.307692307692307},"params":0,"line":188,"cyclomaticDensity":20,"complexity":{"cyclomatic":1,"sloc":{"logical":5,"physical":7},"halstead":{"operators":{"distinct":3,"total":14,"identifiers":["__stripped__"]},"operands":{"distinct":13,"total":22,"identifiers":["__stripped__"]},"length":36,"vocabulary":16,"difficulty":2.5384615384615383,"volume":144,"effort":365.53846153846155,"bugs":0.048,"time":20.307692307692307}}}],"dependencies":[],"maintainability":68.87900301447563,"params":1.263157894736842,"module":"app/scripts/controllers/profile.js"},"jshint":{"messages":[{"severity":"error","line":73,"column":27,"message":"Expected '===' and instead saw '=='.","source":"Expected '{a}' and instead saw '{b}'."},{"severity":"error","line":132,"column":20,"message":"'mold' used out of scope.","source":"'{a}' used out of scope."},{"severity":"error","line":12,"column":81,"message":"'Profile' is defined but never used.","source":"'{a}' is defined but never used."},{"severity":"error","line":12,"column":67,"message":"'ProfilePoint' is defined but never used.","source":"'{a}' is defined but never used."},{"severity":"error","line":130,"column":13,"message":"'mold' is defined but never used.","source":"'{a}' is defined but never used."}]}}